event_count_logger.py
event_count_logger-1.1.1.data/scripts/ecl_log_event
event_count_logger-1.1.1.data/scripts/ecl_master
event_count_logger-1.1.1.data/scripts/ecl_reader
event_count_logger-1.1.1.dist-info/LICENSE
event_count_logger-1.1.1.dist-info/METADATA
event_count_logger-1.1.1.dist-info/WHEEL
event_count_logger-1.1.1.dist-info/top_level.txt
event_count_logger-1.1.1.dist-info/RECORD
