Metadata-Version: 2.1
Name: event-count-logger
Version: 1.1.1
Summary: Count number of events per time interval(s) in a distributed system using shared counters in Redis.
Home-page: https://github.com/CESNET/EventCountLogger
Author: Václav Bartoš
Author-email: bartos@cesnet.cz
License: BSD
Platform: UNKNOWN
Classifier: Programming Language :: Python :: 3
Classifier: License :: OSI Approved :: BSD License
Classifier: Operating System :: OS Independent
Classifier: Intended Audience :: Developers
Classifier: Topic :: Software Development
Classifier: Topic :: System :: Logging
Classifier: Typing :: Typed
Classifier: Development Status :: 4 - Beta
Requires-Python: >=3.6
Requires-Dist: redis
Requires-Dist: apscheduler
Requires-Dist: pyyaml
